periodo_reconciler/__init__.py
periodo_reconciler-0.1.19.data/scripts/periodo-reconciler-py
periodo_reconciler-0.1.19.dist-info/LICENSE
periodo_reconciler-0.1.19.dist-info/METADATA
periodo_reconciler-0.1.19.dist-info/WHEEL
periodo_reconciler-0.1.19.dist-info/entry_points.txt
periodo_reconciler-0.1.19.dist-info/top_level.txt
periodo_reconciler-0.1.19.dist-info/RECORD
